yamlpyconfig/__init__.py
yamlpyconfig/config_cache.py
yamlpyconfig/config_manager.py
yamlpyconfig/py.typed
yamlpyconfig/local_manage/__init__.py
yamlpyconfig/local_manage/local_config_loader.py
yamlpyconfig/local_manage/local_config_manager.py
yamlpyconfig/models/__init__.py
yamlpyconfig/models/algorithm_enum.py
yamlpyconfig/models/base_config_model.py
yamlpyconfig/models/nacos_config.py
yamlpyconfig/models/nacos_config_cache_item.py
yamlpyconfig/nacos_manage/__init__.py
yamlpyconfig/nacos_manage/nacos_config_manager.py
yamlpyconfig/utils/__init__.py
yamlpyconfig/utils/config_merge.py
yamlpyconfig/utils/express_helper.py
yamlpyconfig/utils/crypto/__init__.py
yamlpyconfig/utils/crypto/crypto_algorithm.py
yamlpyconfig/utils/crypto/crypto_algorithm_factory.py
yamlpyconfig/utils/crypto/crypto_helper.py
yamlpyconfig/utils/crypto/impl/SM2Algorithm.py
yamlpyconfig/utils/crypto/impl/SM4Algorithm.py
yamlpyconfig/utils/crypto/impl/SM4AlgorithmHex.py
yamlpyconfig/utils/crypto/impl/__init__.py
yamlpyconfig-0.1.9.dist-info/METADATA
yamlpyconfig-0.1.9.dist-info/WHEEL
yamlpyconfig-0.1.9.dist-info/RECORD
