Metadata-Version: 2.4
Name: yamlpyconfig
Version: 0.1.9
Summary: A unified YAML configuration manager supporting local files and dynamic Nacos configuration with hot-reloading, environment variable substitution, and built-in encryption (SM2/SM4) support.
Author-email: ferdinand <gongjpa@gmail.com>
License-Expression: Apache-2.0 OR MIT
Keywords: aio,application,config,nacos,profile,yaml
Classifier: Development Status :: 5 - Production/Stable
Classifier: Intended Audience :: Developers
Classifier: License :: OSI Approved :: Apache Software License
Classifier: License :: OSI Approved :: MIT License
Classifier: Operating System :: OS Independent
Classifier: Programming Language :: Python :: 3
Classifier: Programming Language :: Python :: 3.12
Classifier: Topic :: Software Development :: Libraries :: Python Modules
Requires-Python: >=3.12
Requires-Dist: cryptography~=46.0
Requires-Dist: gmssl~=3.2
Requires-Dist: pydantic~=2.11
Requires-Dist: pyyaml~=6.0
Provides-Extra: nacos
Requires-Dist: nacos-sdk-python~=2.0; extra == 'nacos'
